{
  "translations": {
    "toolbar": {
      "programsButtom": "Programs"
    },
    "pageProgram": {
      "add topic": "add topic",
      "set order of topics": "set order of topics" 
    },
    "programspage": {
      "choose": "Choose params for searching",
      "count": "Programs was found"
    },
    "pageAuth":{
      "signin": "Sign in",
      "login": "log in",
      "createAccount": "Create new account",
      "haveAccount": "Having an account",
      "signDescription": "Sign in on the internal platform",
      "registerDescription": "Register on the internal platform",
      "name": "Name",
      "Name is required": "Name is required",
      "register": "Register",
      "password": "Password",
      "Password is required": "Password is required",
      "email": "Email Address",
      "Email is required": "Email is required",
      "Must be a valid email": "Must be a valid email",
      "This field must be checked": "This field must be checked",
      "I have read": "I have read the",
      "Terms and Conditions": "Terms and Conditions",
      "I agree with them": "and I agree with them"
    },
    "homepage": {
      "title": "Home",
      "stepbystep": "Step by step",
      "h1": "Learn Arabic",
      "description": "A Platform for learninig arabic by comfort manners. We are students who know how make content a little bit easy and pretty. Platform will provide audio, text and another type content for you in-&nbsp;sha Allah by comfort manners",
      "readytoexplore": "Ready to explore",
      "letsgetstarted": "Let's get started with Programs of Education",
      "gotoprogram": "Go to Programs",
      "chooselevel": "Please select your level"
    },
    "notify": {
      "topic": {
        "was_created": "Topic was created",
        "was_updated": "Topic was update"
      },
      "program": {
        "was_created": "Program was created",
        "was_updated": "Program was update"
      }
    },
    "components": {
      "settings": {
        "save_settings": "Save Settings",
        "title": "Settings",
        "font": "Responsive font sizes",
        "theme": {
          "title":  "Theme",
          "ONE_DARK": "Dark",
          "LIGHT": "Light"
        }
      },
      "account": {
        "dashboard": "Dashboard",
        "logout": "Logout"
      }
    },
    "menu": {
      "programs": "Programs",
      "public": "Public",
      "home": "Home",
      "topics": "Topics",
      "users": "Users",
      "managment": "Managment",
      "myProgram": "My Program",
      "types": "Types of program",
      "createProgram": "Create Program",
      "createTopic": "Create Topic",
      "createUser": "Create User",
      "createType": "Create Type",
      "know more": "Know more",
      "changelog": "Changelog",
      "feedback": "Feedback"
    },
    "chips": {
      "ar": "العربية" ,
      "en": "English" ,
      "ru": "Русский",
      "beginner": "Beginner",
      "elementary": "Elementary",
      "preintermediate": "Pre Intermediate",
      "intermediate": "Intermediate",
      "upperintermediate": "Upper Intermediate" 
    },
    "pageNotFound": {
      "title": "404: Not found",
      "header": "404: The page you are looking for isn’t here",
      "message": "You either tried some shady route or you came here by mistake. Whichever it is, try using the navigation.",
      "backButton": "Back to home"
    },
    "message": {
      "app was update": "Available new version",
      "update": "Update"
    },
    "admin": {
      "my programs": "My programs",
      "new program": "create",
      "cancel": "cancel",
      "edit program": "Edit program",
      "create a new program": "Create a new program",
      "title": "Title",
      "description": "Description",
      "publish": "Publish",
      "level": "Level",
      "language": "Language",
      "type of program": "Type of program" ,
      "create": "create",
      "update": "Update",
      "this is a required field": "this is a required field",
      "do you want to delete program": "Do do you want to delete program and all his topics?",
      "do you want to delete topic": "do you want to delete this topic and all his contents?",
      "my topics": "My topics",
      "add one or more entries": "add one or more entries",
      "create a new topic": "Create a new topic",
      "edit topic": "Edit topic",
      "add entrie": "Add Entrie",
      "save and continue": "Save and Continue",
      "save and open": "Save and Open"
    },
    "table": {
      "title": "Title",
      "program": "Program",
      "user": "User",
      "types": "Types",
      "status": "Status",
      "topics": "Topics",
      "created": "Created",
      "actions": "Actions",
      "rows": "rows",
      "from": "from"
    },
    "filter": {
      "level": "level",
      "language": "explanation language"
    },
    "dropImage": {
      "select one file": "Select one file",
      "select files": "Select files",
      "change file": "You can change the selected file" 
    }
  }
}